AUTHORS
CHANGES
COPYING
MANIFEST.in
Makefile
README.rst
pyproject.toml
setup.cfg
setup.py
bin/pgxn
bin/pgxnclient
docs/Makefile
docs/changes.rst
docs/conf.py
docs/ext.rst
docs/index.rst
docs/install.rst
docs/usage.rst
pgxnclient/__init__.py
pgxnclient/api.py
pgxnclient/archive.py
pgxnclient/cli.py
pgxnclient/errors.py
pgxnclient/i18n.py
pgxnclient/network.py
pgxnclient/spec.py
pgxnclient/tar.py
pgxnclient/zip.py
pgxnclient.egg-info/PKG-INFO
pgxnclient.egg-info/SOURCES.txt
pgxnclient.egg-info/dependency_links.txt
pgxnclient.egg-info/entry_points.txt
pgxnclient.egg-info/not-zip-safe
pgxnclient.egg-info/requires.txt
pgxnclient.egg-info/top_level.txt
pgxnclient/commands/__init__.py
pgxnclient/commands/help.py
pgxnclient/commands/info.py
pgxnclient/commands/install.py
pgxnclient/libexec/README
pgxnclient/libexec/pgxn-check
pgxnclient/libexec/pgxn-download
pgxnclient/libexec/pgxn-help
pgxnclient/libexec/pgxn-info
pgxnclient/libexec/pgxn-install
pgxnclient/libexec/pgxn-load
pgxnclient/libexec/pgxn-mirror
pgxnclient/libexec/pgxn-search
pgxnclient/libexec/pgxn-uninstall
pgxnclient/libexec/pgxn-unload
pgxnclient/utils/__init__.py
pgxnclient/utils/semver.py
pgxnclient/utils/strings.py
pgxnclient/utils/temp.py
pgxnclient/utils/uri.py
tests/__init__.py
tests/test_archives.py
tests/test_commands.py
tests/test_label.py
tests/test_semver.py
tests/test_spec.py
tests/testutils.py
tests/testdata/META-manyext.json
tests/testdata/download.py
tests/testdata/foobar-0.42.1.tar.gz
tests/testdata/foobar-0.42.1.zip
tests/testdata/https%3A%2F%2Fapi.pgxn.org%2Fdist%2Ffirst_last_agg%2F0.1.4%2FMETA.json
tests/testdata/https%3A%2F%2Fapi.pgxn.org%2Fdist%2Ffirst_last_agg.json
tests/testdata/https%3A%2F%2Fapi.pgxn.org%2Fdist%2Ffoobar%2F0.42.1%2FMETA-badsha1.json
tests/testdata/https%3A%2F%2Fapi.pgxn.org%2Fdist%2Ffoobar%2F0.42.1%2FMETA.json
tests/testdata/https%3A%2F%2Fapi.pgxn.org%2Fdist%2Ffoobar%2F0.42.1%2Ffoobar-0.42.1.zip
tests/testdata/https%3A%2F%2Fapi.pgxn.org%2Fdist%2Ffoobar%2F0.43.2b1%2FMETA.json
tests/testdata/https%3A%2F%2Fapi.pgxn.org%2Fdist%2Ffoobar%2F0.43.2b1%2Ffoobar-0.43.2b1.zip
tests/testdata/https%3A%2F%2Fapi.pgxn.org%2Fdist%2Ffoobar.json
tests/testdata/https%3A%2F%2Fapi.pgxn.org%2Fdist%2Fpg_amqp%2F0.3.0%2FMETA.json
