Metadata-Version: 2.1
Name: pgxnclient
Version: 1.3.2
Summary: A command line tool to interact with the PostgreSQL Extension Network.
Home-page: https://pgxn.github.io/pgxnclient/
Author: Daniele Varrazzo
Author-email: daniele.varrazzo@gmail.com
License: BSD
Project-URL: Source, https://github.com/pgxn/pgxnclient
Project-URL: Documentation, https://pgxn.github.io/pgxnclient/
Project-URL: Bug Tracker, https://github.com/pgxn/pgxnclient/issues
Project-URL: Discussion group, https://groups.google.com/group/pgxn-users/
Project-URL: Funding, https://github.com/sponsors/dvarrazzo
Platform: UNKNOWN
Classifier: Development Status :: 5 - Production/Stable
Classifier: Environment :: Console
Classifier: Intended Audience :: Developers
Classifier: Intended Audience :: System Administrators
Classifier: License :: OSI Approved :: BSD License
Classifier: Operating System :: POSIX
Classifier: Programming Language :: Python :: 2
Classifier: Programming Language :: Python :: 3
Classifier: Topic :: Database
Requires-Python: >=2.7,!=3.0.*,!=3.1.*,!=3.2.*,!=3.3.*
Provides-Extra: dev
